pyfastatools-2.5.0.dist-info/WHEEL
pyfastatools-2.5.0.dist-info/RECORD
pyfastatools-2.5.0.dist-info/METADATA
pyfastatools-2.5.0.dist-info/licenses/LICENSE
pyfastatools/_parser.py
pyfastatools/_types.py
pyfastatools/iterator.py
pyfastatools/_fastatools.pyi
pyfastatools/_fastatools.cpython-39-x86_64-linux-gnu.so
pyfastatools/_simple.py
pyfastatools/__init__.py
pyfastatools/utils.py
