Metadata-Version: 2.1
Name: pyfastatools
Version: 2.5.0
Summary: Simple FASTA file tools to parse, edit, subset, split, and perform stats on FASTA files
Author-Email: Cody Martin <codycmar10@gmail.com>
License: MIT License
Classifier: Programming Language :: Python :: 3
Classifier: Programming Language :: Python :: 3.9
Classifier: Programming Language :: Python :: Implementation :: CPython
Classifier: License :: OSI Approved :: MIT License
Project-URL: Homepage, https://github.com/cody-mar10/fasta-tools
Project-URL: Bug tracker, https://github.com/cody-mar10/fasta-tools/issues
Requires-Python: >=3.9
Requires-Dist: more-itertools>=8.2
Requires-Dist: pytest>=8.3; extra == "test"
Requires-Dist: pytest-cov; extra == "test"
Requires-Dist: ruff; extra == "build"
Requires-Dist: mypy; extra == "build"
Requires-Dist: isort; extra == "build"
Requires-Dist: covdefaults; extra == "build"
Requires-Dist: pyfastatools[build]; extra == "dev"
Requires-Dist: pyfastatools[test]; extra == "dev"
Provides-Extra: test
Provides-Extra: build
Provides-Extra: dev
